MANIFEST.in
README.rst
VERSION
setup.py
stepdad/__init__.py
stepdad/main.py
stepdad/run.py
stepdad/utils.py
stepdad.egg-info/PKG-INFO
stepdad.egg-info/SOURCES.txt
stepdad.egg-info/dependency_links.txt
stepdad.egg-info/entry_points.txt
stepdad.egg-info/top_level.txt
stepdad/data/setup.py.template
test/test_all.py