Metadata-Version: 1.1
Name: stepdad
Version: 0.0.4
Summary: Automatically package those singleton modules that keep getting lost. Other organziational benifits.
Home-page: https://github.com/stnbu/stepdad
Author: Mike Burr
Author-email: mburr@unintuitive.org
License: MIT
Download-URL: https://github.com/stnbu/stepdad/archive/master.zip
Keywords: pip,package managementt
Platform: UNKNOWN
Classifier: Development Status :: 3 - Alpha
Classifier: Intended Audience :: Developers
Classifier: License :: OSI Approved :: MIT License
Classifier: Programming Language :: Python :: 2
Classifier: Topic :: Software Development :: Libraries :: Python Modules
Classifier: Topic :: System :: Installation/Setup
Classifier: Topic :: System :: Systems Administration
Classifier: Topic :: Utilities
Provides: stepdad
